{"root": {"value": null, "children": {"A": {"value": "A", "children": {"B": {"value": "B", "children": {"B": {"value": "B", "children": {"A": {"value": "A", "children": {}, "end": true}, "E": {"value": "E", "children": {}, "end": true}}, "end": false}, "E": {"value": "E", "children": {"D": {"value": "D", "children": {}, "end": true}}, "end": false}}, "end": false}, "J": {"value": "J", "children": {"E": {"value": "E", "children": {"E": {"value": "E", "children": {}, "end": true}}, "end": false}}, "end": false}, "K": {"value": "K", "children": {"E": {"value": "E", "children": {"E": {"value": "E", "children": {}, "end": true}}, "end": false}}, "end": false}, "N": {"value": "N", "children": {"K": {"value": "K", "children": {"H": {"value": "H", "children": {}, "end": true}}, "end": false}, "N": {"value": "N", "children": {"A": {"value": "A", "children": {}, "end": true}}, "end": false}}, "end": false}}, "end": false}, "B": {"value": "B", "children": {"A": {"value": "A", "children": {"B": {"value": "B", "children": {"A": {"value": "A", "children": {}, "end": true}, "E": {"value": "E", "children": {}, "end": true}}, "end": false}, "D": {"value": "D", "children": {"E": {"value": "E", "children": {}, "end": true}}, "end": false}, "F": {"value": "F", "children": {"F": {"value": "F", "children": {}, "end": true}}, "end": false}, "K": {"value": "K", "children": {"E": {"value": "E", "children": {}, "end": true}}, "end": false}, "N": {"value": "N", "children": {"D": {"value": "D", "children": {}, "end": true}, "E": {"value": "E", "children": {}, "end": true}, "K": {"value": "K", "children": {}, "end": true}}, "end": false}}, "end": false}, "E": {"value": "E", "children": {"A": {"value": "A", "children": {"D": {"value": "D", "children": {}, "end": true}, "K": {"value": "K", "children": {}, "end": true}, "N": {"value": "N", "children": {}, "end": true}}, "end": false}, "E": {"value": "E", "children": {"F": {"value": "F", "children": {}, "end": true}, "N": {"value": "N", "children": {}, "end": true}}, "end": false}, "N": {"value": "N", "children": {"D": {"value": "D", "children": {}, "end": true}, "E": {"value": "E", "children": {}, "end": true}}, "end": false}}, "end": false}}, "end": false}, "D": {"value": "D", "children": {"A": {"value": "A", "children": {"D": {"value": "D", "children": {"A": {"value": "A", "children": {}, "end": true}}, "end": false}, "F": {"value": "F", "children": {"F": {"value": "F", "children": {}, "end": true}}, "end": false}, "N": {"value": "N", "children": {"K": {"value": "K", "children": {}, "end": true}}, "end": false}}, "end": false}, "E": {"value": "E", "children": {"A": {"value": "A", "children": {"D": {"value": "D", "children": {}, "end": true}, "F": {"value": "F", "children": {}, "end": true}, "N": {"value": "N", "children": {}, "end": true}}, "end": false}, "E": {"value": "E", "children": {"D": {"value": "D", "children": {}, "end": true}}, "end": false}, "K": {"value": "K", "children": {"E": {"value": "E", "children": {}, "end": true}}, "end": false}, "N": {"value": "N", "children": {"E": {"value": "E", "children": {}, "end": true}}, "end": false}}, "end": false}, "H": {"value": "H", "children": {"A": {"value": "A", "children": {"K": {"value": "K", "children": {}, "end": true}}, "end": false}}, "end": false}}, "end": false}, "E": {"value": "E", "children": {"K": {"value": "K", "children": {"E": {"value": "E", "children": {"D": {"value": "D", "children": {}, "end": true}}, "end": false}}, "end": false}}, "end": false}, "F": {"value": "F", "children": {"A": {"value": "A", "children": {"D": {"value": "D", "children": {"E": {"value": "E", "children": {}, "end": true}}, "end": false}, "K": {"value": "K", "children": {"E": {"value": "E", "children": {}, "end": true}}, "end": false}, "N": {"value": "N", "children": {"E": {"value": "E", "children": {}, "end": true}}, "end": false}}, "end": false}, "E": {"value": "E", "children": {"E": {"value": "E", "children": {"D": {"value": "D", "children": {}, "end": true}}, "end": false}, "N": {"value": "N", "children": {"D": {"value": "D", "children": {}, "end": true}}, "end": false}}, "end": false}}, "end": false}, "H": {"value": "H", "children": {"A": {"value": "A", "children": {"A": {"value": "A", "children": {"F": {"value": "F", "children": {}, "end": true}}, "end": false}, "D": {"value": "D", "children": {"E": {"value": "E", "children": {}, "end": true}, "J": {"value": "J", "children": {}, "end": true}}, "end": false}, "E": {"value": "E", "children": {"D": {"value": "D", "children": {}, "end": true}, "N": {"value": "N", "children": {}, "end": true}}, "end": false}, "H": {"value": "H", "children": {"A": {"value": "A", "children": {}, "end": true}}, "end": false}, "J": {"value": "J", "children": {"J": {"value": "J", "children": {}, "end": true}}, "end": false}, "K": {"value": "K", "children": {"E": {"value": "E", "children": {}, "end": true}}, "end": false}, "N": {"value": "N", "children": {"D": {"value": "D", "children": {}, "end": true}, "K": {"value": "K", "children": {}, "end": true}}, "end": false}}, "end": false}, "E": {"value": "E", "children": {"A": {"value": "A", "children": {"D": {"value": "D", "children": {}, "end": true}}, "end": false}, "B": {"value": "B", "children": {"E": {"value": "E", "children": {}, "end": true}}, "end": false}, "E": {"value": "E", "children": {"D": {"value": "D", "children": {}, "end": true}}, "end": false}}, "end": false}}, "end": false}, "J": {"value": "J", "children": {"A": {"value": "A", "children": {"D": {"value": "D", "children": {"E": {"value": "E", "children": {}, "end": true}}, "end": false}, "K": {"value": "K", "children": {"E": {"value": "E", "children": {}, "end": true}}, "end": false}, "N": {"value": "N", "children": {"E": {"value": "E", "children": {}, "end": true}}, "end": false}}, "end": false}, "E": {"value": "E", "children": {"A": {"value": "A", "children": {"N": {"value": "N", "children": {}, "end": true}}, "end": false}, "E": {"value": "E", "children": {"D": {"value": "D", "children": {}, "end": true}}, "end": false}, "F": {"value": "F", "children": {"E": {"value": "E", "children": {}, "end": true}}, "end": false}}, "end": false}}, "end": false}, "K": {"value": "K", "children": {"A": {"value": "A", "children": {"K": {"value": "K", "children": {"A": {"value": "A", "children": {}, "end": true}}, "end": false}, "N": {"value": "N", "children": {"A": {"value": "A", "children": {}, "end": true}, "E": {"value": "E", "children": {}, "end": true}}, "end": false}}, "end": false}, "E": {"value": "E", "children": {"E": {"value": "E", "children": {"F": {"value": "F", "children": {}, "end": true}, "K": {"value": "K", "children": {}, "end": true}, "N": {"value": "N", "children": {}, "end": true}}, "end": false}}, "end": false}, "H": {"value": "H", "children": {"A": {"value": "A", "children": {"F": {"value": "F", "children": {}, "end": true}, "N": {"value": "N", "children": {}, "end": true}}, "end": false}}, "end": false}, "N": {"value": "N", "children": {"E": {"value": "E", "children": {"E": {"value": "E", "children": {}, "end": true}}, "end": false}}, "end": false}}, "end": false}, "N": {"value": "N", "children": {"A": {"value": "A", "children": {"A": {"value": "A", "children": {"N": {"value": "N", "children": {}, "end": true}}, "end": false}, "B": {"value": "B", "children": {"E": {"value": "E", "children": {}, "end": true}}, "end": false}, "D": {"value": "D", "children": {"A": {"value": "A", "children": {}, "end": true}}, "end": false}, "N": {"value": "N", "children": {"A": {"value": "A", "children": {}, "end": true}}, "end": false}}, "end": false}, "E": {"value": "E", "children": {"E": {"value": "E", "children": {"D": {"value": "D", "children": {}, "end": true}}, "end": false}, "N": {"value": "N", "children": {"E": {"value": "E", "children": {}, "end": true}}, "end": false}}, "end": false}}, "end": false}}, "end": false}, "count": 72}